mcconv/__init__.py
mcconv/detect.py
mcconv/eic_smear_reader.py
mcconv/eic_smear_to_hepmc.py
mcconv/file_types.py
mcconv/generic_reader.py
mcconv/hepmc_convert.py
mcconv/hepmc_reader.py
mcconv/lund_to_hepmc.py
mcconv/version.py
mcconv/formats/__init__.py
mcconv/formats/beagle.py
mcconv/formats/lund.py
mcconv-0.0.15.dist-info/LICENSE
mcconv-0.0.15.dist-info/METADATA
mcconv-0.0.15.dist-info/WHEEL
mcconv-0.0.15.dist-info/entry_points.txt
mcconv-0.0.15.dist-info/top_level.txt
mcconv-0.0.15.dist-info/RECORD
