Metadata-Version: 2.1
Name: mcconv
Version: 0.0.15
Summary: EIC Monte-Carlo file converter
Home-page: https://eicweb.phy.anl.gov/monte_carlo/mcconv
Author: Dmitry Romanov
Author-email: romanov@jlab.org
License: MIT
Platform: UNKNOWN
Classifier: Development Status :: 4 - Beta
Classifier: License :: OSI Approved :: MIT License
Classifier: Programming Language :: Python :: 3.6
Classifier: Programming Language :: Python :: 3.7
Classifier: Programming Language :: Python :: 3.8
Classifier: Programming Language :: Python :: 3.9
Classifier: Programming Language :: Python :: 3.10
License-File: LICENSE
Requires-Dist: click
Requires-Dist: HepMC3
Requires-Dist: uproot (>=4)
Requires-Dist: awkward
Requires-Dist: numpy
Requires-Dist: vector
